text_counter/__init__.py
text_counter/main.py
text_counter-0.1.0.dist-info/METADATA
text_counter-0.1.0.dist-info/WHEEL
text_counter-0.1.0.dist-info/entry_points.txt
text_counter-0.1.0.dist-info/licenses/LICENSE
text_counter-0.1.0.dist-info/RECORD
