Metadata-Version: 2.4
Name: text-counter
Version: 0.1.0
Summary: An MCP server that calculates basic text metrics for input text.
Project-URL: Homepage, https://github.com/gws8820/text-counter
Project-URL: Repository, https://github.com/gws8820/text-counter
License-Expression: MIT
License-File: LICENSE
Requires-Python: >=3.10
Requires-Dist: mcp[cli]>=1.14.0
